figexport/config.py
figexport/export_manager.py
figexport/main.py
figexport/utils.py
figexport/export/drawio_exporter.py
figexport/export/enums.py
figexport/export/fig_exporter.py
figexport/export/puml_exporter.py
figexport/export/svg_exporter.py
figexport/export/tex_exporter.py
figexport-0.2.5.dist-info/licenses/LICENSE
figexport-0.2.5.dist-info/METADATA
figexport-0.2.5.dist-info/WHEEL
figexport-0.2.5.dist-info/entry_points.txt
figexport-0.2.5.dist-info/top_level.txt
figexport-0.2.5.dist-info/RECORD
