Metadata-Version: 2.4
Name: figexport
Version: 0.2.5
Summary: A command line tool for automatic export of figures of various formats to PDF/SVG/PNG/JPG files.
Author-email: Houssem Guissouma <houssem.guissouma@gmx.de>
License: MIT
Project-URL: Homepage, https://github.com/HouGui/figexport
Requires-Python: >=3.10
License-File: LICENSE
Requires-Dist: cairosvg
Requires-Dist: requests
Provides-Extra: dev
Requires-Dist: pytest; extra == "dev"
Requires-Dist: pytest-cov; extra == "dev"
Requires-Dist: pyinstaller; extra == "dev"
Requires-Dist: build; extra == "dev"
Requires-Dist: twine; extra == "dev"
Dynamic: license-file
